enlp/__init__.py
enlp/language_models.py
enlp/pipeline.py
enlp/version.py
enlp/processing/__init__.py
enlp/processing/stdtools.py
enlp/understanding/__init__.py
enlp/understanding/distributions.py
enlp/understanding/keywords.py
enlp/understanding/linguistic.py
enlp/understanding/sentiment.py
enlp/understanding/topics.py
enlp/understanding/vectors.py
enlp/visualisation/__init__.py
enlp/visualisation/freq_distribution.py
enlp/visualisation/word_vectors.py
enlp-0.0.0.dist-info/LICENSE.md
enlp-0.0.0.dist-info/METADATA
enlp-0.0.0.dist-info/WHEEL
enlp-0.0.0.dist-info/top_level.txt
enlp-0.0.0.dist-info/zip-safe
enlp-0.0.0.dist-info/RECORD
