Metadata-Version: 2.1
Name: enlp
Version: 0.0.0
Summary: 
Home-page: UNKNOWN
Author: Equinor ASA
Author-email: clbi@equinor.com
License: UNKNOWN
Keywords: nlp
Platform: UNKNOWN
Classifier: Development Status :: 3 - Alpha
Classifier: Intended Audience :: Developers
Classifier: Intended Audience :: Science/Research
Classifier: License :: OSI Approved :: GNU Lesser General Public License v3 or later (LGPLv3+)
Classifier: Natural Language :: English
Classifier: Programming Language :: Python :: 3.7
Classifier: Topic :: Scientific/Engineering :: Mathematics
Requires-Dist: numpy
Requires-Dist: matplotlib
Requires-Dist: pandas
Requires-Dist: spacy (==2.0.18)
Requires-Dist: nltk
Requires-Dist: gensim
Requires-Dist: scikit-learn
Requires-Dist: rake-nltk
Requires-Dist: wordcloud
